aws_resource_validator/class_definitions.py
aws_resource_validator/models.py
aws_resource_validator-1.0.2.dist-info/LICENSE
aws_resource_validator-1.0.2.dist-info/METADATA
aws_resource_validator-1.0.2.dist-info/WHEEL
aws_resource_validator-1.0.2.dist-info/RECORD
