Metadata-Version: 2.3
Name: aws-resource-validator
Version: 1.0.2
Summary: Validate, get validation patterns and generate valid AWS resource names (for testing \ mocks)
License: Apache-2.0
Author: Alexy Grabov
Author-email: alexy.grabov@gmail.com
Requires-Python: >=3.9,<4.0
Classifier: License :: OSI Approved :: Apache Software License
Classifier: Programming Language :: Python :: 3
Classifier: Programming Language :: Python :: 3.9
Classifier: Programming Language :: Python :: 3.10
Classifier: Programming Language :: Python :: 3.11
Classifier: Programming Language :: Python :: 3.12
Classifier: Programming Language :: Python :: 3.13
Requires-Dist: botocore
Requires-Dist: exrex
Requires-Dist: pydantic (>=2.8.2,<3.0.0)
